PyThinkDesign/Application.py
PyThinkDesign/Geo3d.py
PyThinkDesign/WrapperCore.dll
PyThinkDesign/_Application.pyd
PyThinkDesign/_Geo3d.pyd
PyThinkDesign/__init__.py
PyThinkDesign/tdApplication.dll
PyThinkDesign/tdGeo3d.dll
PyThinkDesign/tdWrapperCore.dll
pythinkdesign-0.1.13.dist-info/METADATA
pythinkdesign-0.1.13.dist-info/WHEEL
pythinkdesign-0.1.13.dist-info/top_level.txt
pythinkdesign-0.1.13.dist-info/RECORD
